{ "editionButtons" : 
	[
		{
			"title" : "div",
			"htmlBefore" : "<div>",
			"htmlAfter" :  "</div>"
		},
		{
			"title" : "p",
			"htmlBefore" : "<p>",
			"htmlAfter" : "</p>"
		},
		{
			"title" : "span",
			"htmlBefore" : "<span>",
			"htmlAfter" : "</span>"
		},
		{
			"title" : "a",
			"htmlBefore" : "<a target='_blank' href=''>",
			"htmlAfter" : "</a>"
		},
		{
			"title": "&lt;li&gt;●&lt;li&gt;",
			"htmlBefore": "<li>",
			"htmlAfter": "</li>"
		}, 	
		{
			"title" : "<span style='color:white;background-color:red'>Red</span>",
			"htmlBefore" : "<span style='color:white;background-color:red'>",
			"htmlAfter" : "</span>"
		}, 
		{
			"title" : "<span style='color:white;background-color:green'>Green</span>",
			"htmlBefore" : "<span style='color:white;background-color:green'>",
			"htmlAfter" : "</span>"
		}, 
		{
			"title" : "<span style='color:white;background-color:blue'>Blue</span>",
			"htmlBefore" : "<span style='color:white;background-color:blue'>",
			"htmlAfter" : "</span>"
		}, 
		{
			"title" : "<span style='color:white;background-color:brown'>Brown</span>",
			"htmlBefore" : "<span style='color:white;background-color:brown'>",
			"htmlAfter" : "</span>"
		}, 
		{
			"title" : "<span style='color:white;background-color:black'>Black</span>",
			"htmlBefore" : "<span style='color:white;background-color:black'>",
			"htmlAfter" : "</span>"
		}, 
		{
			"title" : "<span style='border:solid 0.1em'>White</span>",
			"htmlBefore" : "<span style='border:solid 0.1em'>",
			"htmlAfter" : "</span>"
		},
		{
			"title": "⮜",
			"htmlBefore": "⮜"
		}, 
		{
			"title": "⮞",
			"htmlBefore": "⮞"
		}, 
		{
			"title" : "<span style='color:white;background-color:blue'>&nbsp;&#x1F6B2;&nbsp;</span><span style='color:white;background-color:red'>&nbsp;</span>",
			"htmlBefore" : "<span style='color:white;background-color:blue'>&nbsp;&#x1F6B2;&nbsp;</span><span style='color:white;background-color:red'>",
			"htmlAfter" : "</span>"
		},
		{
			"title": "&#x1F6B2;",
			"htmlBefore": "&nbsp;&#x1F6B2;&nbsp;"
		}, 
		{
			"title" : "<span style='text-decoration: underline'>U</span>",
			"htmlBefore" : "<span style='text-decoration: underline'>",
			"htmlAfter" : "</span>"
		},
		{
			"title": "Å",
			"htmlBefore": "Å"
		}, 
		{
			"title": "å",
			"htmlBefore": "å"
		}, 
		{
			"title": "Æ",
			"htmlBefore": "Æ"
		}, 
		{
			"title": "æ",
			"htmlBefore": "æ"
		}, 
		{
			"title": "Ø",
			"htmlBefore": "Ø"
		}, 
		{
			"title": "ø",
			"htmlBefore": "ø"
		},
		{
			"title": "&amp;nbsp;",
			"htmlBefore": "&nbsp;"
		}
	],
	"preDefinedIconsList" :
	[
		{
			"name" : "SVG icon from OSM",
			"icon" : "SvgIcon",
			"tooltip" : "SVG icon from OSM",
			"width" : 40,
			"height" : 40
		},
		{
			"name" : "Airport",
			"icon" : "<div class='TravelNotes-MapNote TravelNotes-MapNoteCategory-0001'></div>",
			"tooltip" : "Airport",
			"width" : 40,
			"height" : 40
		},
		{
			"name" : "Ascent",
			"icon" : "<div class='TravelNotes-MapNote TravelNotes-MapNoteCategory-0002'></div>",
			"tooltip" : "Ascent",
			"width" : 40,
			"height" : 40
		},
		{
			"name" : "ATM",
			"icon" : "<div class='TravelNotes-MapNote TravelNotes-MapNoteCategory-0003'></div>",
			"tooltip" : "ATM",
			"width" : 40,
			"height" : 40
		},
		{
			"name" : "Attention",
			"icon" : "<div class='TravelNotes-MapNote TravelNotes-MapNoteCategory-0004'></div>",
			"tooltip" : "Attention",
			"width" : 40,
			"height" : 40
		},
		{
			"name" : "Bikes allowed",
			"icon" : "<div class='TravelNotes-MapNote TravelNotes-MapNoteCategory-0005'></div>",
			"tooltip" : "Bikes allowed",
			"width" : 40,
			"height" : 40
		},
		{
			"name" : "Bus station",
			"icon" : "<div class='TravelNotes-MapNote TravelNotes-MapNoteCategory-0006'></div>",
			"tooltip" : "Bus station",
			"width" : 40,
			"height" : 40
		},
		{
			"name" : "Photo",
			"icon" : "<div class='TravelNotes-MapNote TravelNotes-MapNoteCategory-0007'></div>",
			"tooltip" : "Photo",
			"width" : 40,
			"height" : 40
		},
		{
			"name" : "Camping",
			"icon" : "<div class='TravelNotes-MapNote TravelNotes-MapNoteCategory-0008'></div>",
			"tooltip" : "Camping",
			"width" : 40,
			"height" : 40
		},
		{
			"name" : "Ferry terminal",
			"icon" : "<div class='TravelNotes-MapNote TravelNotes-MapNoteCategory-0009'></div>",
			"tooltip" : "Ferry terminal",
			"width" : 40,
			"height" : 40
		},
		{
			"name" : "Hostel",
			"icon" : "<div class='TravelNotes-MapNote TravelNotes-MapNoteCategory-0010'></div>",
			"tooltip" : "Hostel",
			"width" : 40,
			"height" : 40
		},
		{
			"name" : "Information office",
			"icon" : "<div class='TravelNotes-MapNote TravelNotes-MapNoteCategory-0011'></div>",
			"tooltip" : "Information office",
			"width" : 40,
			"height" : 40
		},
		{
			"name" : "National park",
			"icon" : "<div class='TravelNotes-MapNote TravelNotes-MapNoteCategory-0012'></div>",
			"tooltip" : "National park",
			"width" : 40,
			"height" : 40
		},
		{
			"name" : "Bike not allowed",
			"icon" : "<div class='TravelNotes-MapNote TravelNotes-MapNoteCategory-0013'></div>",
			"tooltip" : "Bike not allowed",
			"width" : 40,
			"height" : 40
		},
		{
			"name" : "AONB",
			"icon" : "<div class='TravelNotes-MapNote TravelNotes-MapNoteCategory-0014'></div>",
			"tooltip" : "AONB",
			"width" : 40,
			"height" : 40
		},
		{
			"name" : "Bicycle repair station",
			"icon" : "<div class='TravelNotes-MapNote TravelNotes-MapNoteCategory-0015'></div>",
			"tooltip" : "Bicycle repair station",
			"width" : 40,
			"height" : 40
		},
		{
			"name" : "Supermarket",
			"icon" : "<div class='TravelNotes-MapNote TravelNotes-MapNoteCategory-0016'></div>",
			"tooltip" : "Supermarket",
			"width" : 40,
			"height" : 40
		},
		{
			"name" : "Rescue station",
			"icon" : "<div class='TravelNotes-MapNote TravelNotes-MapNoteCategory-0017'></div>",
			"tooltip" : "Rescue station",
			"width" : 40,
			"height" : 40
		},
		{
			"name" : "Stop",
			"icon" : "<div class='TravelNotes-MapNote TravelNotes-MapNoteCategory-0018'></div>",
			"tooltip" : "Stop",
			"width" : 40,
			"height" : 40
		},
		{
			"name" : "Table",
			"icon" : "<div class='TravelNotes-MapNote TravelNotes-MapNoteCategory-0019'></div>",
			"tooltip" : "Table",
			"width" : 40,
			"height" : 40
		},
		{
			"name" : "Toilets",
			"icon" : "<div class='TravelNotes-MapNote TravelNotes-MapNoteCategory-0020'></div>",
			"tooltip" : "Toilets",
			"width" : 40,
			"height" : 40
		},
		{
			"name" : "Train station",
			"icon" : "<div class='TravelNotes-MapNote TravelNotes-MapNoteCategory-0021'></div>",
			"tooltip" : "Train station",
			"width" : 40,
			"height" : 40
		},
		{
			"name" : "Tunnel",
			"icon" : "<div class='TravelNotes-MapNote TravelNotes-MapNoteCategory-0022'></div>",
			"tooltip" : "Tunnel",
			"width" : 40,
			"height" : 40
		},
		{
			"name" : "Water point",
			"icon" : "<div class='TravelNotes-MapNote TravelNotes-MapNoteCategory-0023'></div>",
			"tooltip" : "Water point",
			"width" : 40,
			"height" : 40
		},
		{
			"name" : "B & B",
			"icon" : "<div class='TravelNotes-MapNote TravelNotes-MapNoteCategory-0024'></div>",
			"tooltip" : "B & B",
			"width" : 40,
			"height" : 40
		},
		{
			"name" : "Coffeehouse",
			"icon" : "<div class='TravelNotes-MapNote TravelNotes-MapNoteCategory-0025'></div>",
			"tooltip" : "Coffeehouse",
			"width" : 40,
			"height" : 40
		},
		{
			"name" : "Restaurant",
			"icon" : "<div class='TravelNotes-MapNote TravelNotes-MapNoteCategory-0026'></div>",
			"tooltip" : "Restaurant",
			"width" : 40,
			"height" : 40
		},
		{
			"name" : "Hotel",
			"icon" : "<div class='TravelNotes-MapNote TravelNotes-MapNoteCategory-0027'></div>",
			"tooltip" : "Hotel",
			"width" : 40,
			"height" : 40
		},
		{
			"name" : "Start",
			"icon" : "<div class='TravelNotes-MapNote TravelNotes-MapNoteCategory-0028'></div>",
			"tooltip" : "Start",
			"width" : 40,
			"height" : 40
		},
		{
			"name" : "Laundry",
			"icon" : "<div class='TravelNotes-MapNote TravelNotes-MapNoteCategory-0029'></div>",
			"tooltip" : "Laundry",
			"width" : 40,
			"height" : 40
		},
		{
			"name" : "Travel agency",
			"icon" : "<div class='TravelNotes-MapNote TravelNotes-MapNoteCategory-0030'></div>",
			"tooltip" : "Travel agency",
			"width" : 40,
			"height" : 40
		},
		{
			"name" : "Convenience",
			"icon" : "<div class='TravelNotes-MapNote TravelNotes-MapNoteCategory-0031'></div>",
			"tooltip" : "Convenience",
			"width" : 40,
			"height" : 40
		},
		{
			"name" : "Greengrocer",
			"icon" : "<div class='TravelNotes-MapNote TravelNotes-MapNoteCategory-0032'></div>",
			"tooltip" : "Greengrocer",
			"width" : 40,
			"height" : 40
		},
		{
			"name" : "Bakery",
			"icon" : "<div class='TravelNotes-MapNote TravelNotes-MapNoteCategory-0033'></div>",
			"tooltip" : "Bakery",
			"width" : 40,
			"height" : 40
		},
		{
			"name" : "Pastry",
			"icon" : "<div class='TravelNotes-MapNote TravelNotes-MapNoteCategory-0034'></div>",
			"tooltip" : "Pastry",
			"width" : 40,
			"height" : 40
		},
		{
			"name" : "Clothes",
			"icon" : "<div class='TravelNotes-MapNote TravelNotes-MapNoteCategory-0035'></div>",
			"tooltip" : "Clothes",
			"width" : 40,
			"height" : 40
		},
		{
			"name" : "Shoes",
			"icon" : "<div class='TravelNotes-MapNote TravelNotes-MapNoteCategory-0036'></div>",
			"tooltip" : "Shoes",
			"width" : 40,
			"height" : 40
		},
		{
			"name" : "Sport",
			"icon" : "<div class='TravelNotes-MapNote TravelNotes-MapNoteCategory-0037'></div>",
			"tooltip" : "Sport",
			"width" : 40,
			"height" : 40
		},
		{
			"name" : "Bank",
			"icon" : "<div class='TravelNotes-MapNote TravelNotes-MapNoteCategory-0038'></div>",
			"tooltip" : "Bank",
			"width" : 40,
			"height" : 40
		},
		{
			"name" : "Bureau de change",
			"icon" : "<div class='TravelNotes-MapNote TravelNotes-MapNoteCategory-0039'></div>",
			"tooltip" : "Bureau de change",
			"width" : 40,
			"height" : 40
		},
		{
			"name" : "Bar",
			"icon" : "<div class='TravelNotes-MapNote TravelNotes-MapNoteCategory-0040'></div>",
			"tooltip" : "Bar",
			"width" : 40,
			"height" : 40
		},
		{
			"name" : "Pub",
			"icon" : "<div class='TravelNotes-MapNote TravelNotes-MapNoteCategory-0041'></div>",
			"tooltip" : "Pub",
			"width" : 40,
			"height" : 40
		},
		{
			"name" : "Bench",
			"icon" : "<div class='TravelNotes-MapNote TravelNotes-MapNoteCategory-0042'></div>",
			"tooltip" : "Bench",
			"width" : 40,
			"height" : 40
		},
		{
			"name" : "Barbecue",
			"icon" : "<div class='TravelNotes-MapNote TravelNotes-MapNoteCategory-0043'></div>",
			"tooltip" : "Barbecue",
			"width" : 40,
			"height" : 40
		},
		{
			"name" : "Shelter",
			"icon" : "<div class='TravelNotes-MapNote TravelNotes-MapNoteCategory-0044'></div>",
			"tooltip" : "Shelter",
			"width" : 40,
			"height" : 40
		},
		{
			"name" : "Recycling container",
			"icon" : "<div class='TravelNotes-MapNote TravelNotes-MapNoteCategory-0045'></div>",
			"tooltip" : "Recycling container",
			"width" : 40,
			"height" : 40
		},
		{
			"name" : "Waste disposal",
			"icon" : "<div class='TravelNotes-MapNote TravelNotes-MapNoteCategory-0046'></div>",
			"tooltip" : "Waste disposal",
			"width" : 40,
			"height" : 40
		},
		{
			"name" : "Holiday cottage",
			"icon" : "<div class='TravelNotes-MapNote TravelNotes-MapNoteCategory-0047'></div>",
			"tooltip" : "Holiday cottage",
			"width" : 40,
			"height" : 40
		},
		{
			"name" : "Wilderness hut",
			"icon" : "<div class='TravelNotes-MapNote TravelNotes-MapNoteCategory-0048'></div>",
			"tooltip" : "Wilderness hut",
			"width" : 40,
			"height" : 40
		},
		{
			"name" : "Alpine hut",
			"icon" : "<div class='TravelNotes-MapNote TravelNotes-MapNoteCategory-0049'></div>",
			"tooltip" : "Alpine hut",
			"width" : 40,
			"height" : 40
		},
		{
			"name" : "Tickets vending machine",
			"icon" : "<div class='TravelNotes-MapNote TravelNotes-MapNoteCategory-0050'></div>",
			"tooltip" : "Tickets vending machine",
			"width" : 40,
			"height" : 40
		},
		{
			"name" : "Bus stop",
			"icon" : "<div class='TravelNotes-MapNote TravelNotes-MapNoteCategory-0051'></div>",
			"tooltip" : "Bus stop",
			"width" : 40,
			"height" : 40
		},
		{
			"name" : "Taxi",
			"icon" : "<div class='TravelNotes-MapNote TravelNotes-MapNoteCategory-0052'></div>",
			"tooltip" : "Taxi",
			"width" : 40,
			"height" : 40
		},
		{
			"name" : "Car rental",
			"icon" : "<div class='TravelNotes-MapNote TravelNotes-MapNoteCategory-0053'></div>",
			"tooltip" : "Car rental",
			"width" : 40,
			"height" : 40
		},
		{
			"name" : "Fuel station",
			"icon" : "<div class='TravelNotes-MapNote TravelNotes-MapNoteCategory-0054'></div>",
			"tooltip" : "Fuel station",
			"width" : 40,
			"height" : 40
		},
		{
			"name" : "Car parking",
			"icon" : "<div class='TravelNotes-MapNote TravelNotes-MapNoteCategory-0055'></div>",
			"tooltip" : "Car parking",
			"width" : 40,
			"height" : 40
		},
		{
			"name" : "Car repair",
			"icon" : "<div class='TravelNotes-MapNote TravelNotes-MapNoteCategory-0056'></div>",
			"tooltip" : "Car repair",
			"width" : 40,
			"height" : 40
		},
		{
			"name" : "Bicycle parking",
			"icon" : "<div class='TravelNotes-MapNote TravelNotes-MapNoteCategory-0057'></div>",
			"tooltip" : "Bicycle parking",
			"width" : 40,
			"height" : 40
		},
		{
			"name" : "Bicycle rental",
			"icon" : "<div class='TravelNotes-MapNote TravelNotes-MapNoteCategory-0058'></div>",
			"tooltip" : "Bicycle rental",
			"width" : 40,
			"height" : 40
		},
		{
			"name" : "Bicycle shop",
			"icon" : "<div class='TravelNotes-MapNote TravelNotes-MapNoteCategory-0059'></div>",
			"tooltip" : "Bicycle shop",
			"width" : 40,
			"height" : 40
		},
		{
			"name" : "Clinic",
			"icon" : "<div class='TravelNotes-MapNote TravelNotes-MapNoteCategory-0060'></div>",
			"tooltip" : "Clinic",
			"width" : 40,
			"height" : 40
		},
		{
			"name" : "Doctor",
			"icon" : "<div class='TravelNotes-MapNote TravelNotes-MapNoteCategory-0061'></div>",
			"tooltip" : "Doctor",
			"width" : 40,
			"height" : 40
		},
		{
			"name" : "Hospital",
			"icon" : "<div class='TravelNotes-MapNote TravelNotes-MapNoteCategory-0062'></div>",
			"tooltip" : "Hospital",
			"width" : 40,
			"height" : 40
		},
		{
			"name" : "Dentist",
			"icon" : "<div class='TravelNotes-MapNote TravelNotes-MapNoteCategory-0063'></div>",
			"tooltip" : "Dentist",
			"width" : 40,
			"height" : 40
		},
		{
			"name" : "Pharmacy",
			"icon" : "<div class='TravelNotes-MapNote TravelNotes-MapNoteCategory-0064'></div>",
			"tooltip" : "Pharmacy",
			"width" : 40,
			"height" : 40
		},
		{
			"name" : "Optician",
			"icon" : "<div class='TravelNotes-MapNote TravelNotes-MapNoteCategory-0065'></div>",
			"tooltip" : "Optician",
			"width" : 40,
			"height" : 40
		},
		{
			"name" : "Embassy",
			"icon" : "<div class='TravelNotes-MapNote TravelNotes-MapNoteCategory-0066'></div>",
			"tooltip" : "Embassy",
			"width" : 40,
			"height" : 40
		},
		{
			"name" : "Post office",
			"icon" : "<div class='TravelNotes-MapNote TravelNotes-MapNoteCategory-0067'></div>",
			"tooltip" : "Post office",
			"width" : 40,
			"height" : 40
		},
		{
			"name" : "Public bath",
			"icon" : "<div class='TravelNotes-MapNote TravelNotes-MapNoteCategory-0068'></div>",
			"tooltip" : "Public bath",
			"width" : 40,
			"height" : 40
		},
		{
			"name" : "Shower",
			"icon" : "<div class='TravelNotes-MapNote TravelNotes-MapNoteCategory-0069'></div>",
			"tooltip" : "Shower",
			"width" : 40,
			"height" : 40
		},
		{
			"name" : "Police",
			"icon" : "<div class='TravelNotes-MapNote TravelNotes-MapNoteCategory-0070'></div>",
			"tooltip" : "Police",
			"width" : 40,
			"height" : 40
		},
		{
			"name" : "My notes",
			"icon" : "<div class='TravelNotes-MapNote TravelNotes-MapNoteCategory-0071'></div>",
			"tooltip" : "My notes",
			"width" : 40,
			"height" : 40
		},
		{
			"name" : "Caravan site",
			"icon" : "<div class='TravelNotes-MapNote TravelNotes-MapNoteCategory-0072'></div>",
			"tooltip" : "Caravan site",
			"width" : 40,
			"height" : 40
		},
		{
			"name" : "Bicycle node point",
			"icon" : "<div class='TravelNotes-MapNote TravelNotes-MapNoteCategory-0073'><svg viewBox='0 0 20 20'><text x='10' y='14'>00</text></svg></div>",
			"tooltip" : "Bicycle node point",
			"width" : 40,
			"height" : 40
		}
	]
}